list_like/__init__.py
list_like-0.1.0.dist-info/WHEEL
list_like-0.1.0.dist-info/METADATA
list_like-0.1.0.dist-info/RECORD
