Metadata-Version: 2.1
Name: list-like
Version: 0.1.0
Summary: Test whether an object is an iterable that's not a string or mapping
License: MIT
Author: Corentin Moevus
Author-email: c.moevus@gmail.com
Requires-Python: >=3.10,<4.0
Classifier: License :: OSI Approved :: MIT License
Classifier: Programming Language :: Python :: 3
Classifier: Programming Language :: Python :: 3.10
